platformer/__init__.py
platformer/main.py
platformer/img/blob.png
platformer/img/coin.png
platformer/img/coin.wav
platformer/img/dirt.png
platformer/img/exit.png
platformer/img/exit_btn.png
platformer/img/game_over.wav
platformer/img/ghost.png
platformer/img/grass.png
platformer/img/guy1.png
platformer/img/guy2.png
platformer/img/guy3.png
platformer/img/guy4.png
platformer/img/jump.wav
platformer/img/lava.png
platformer/img/load_btn.png
platformer/img/music.wav
platformer/img/platform.png
platformer/img/platform_x.png
platformer/img/platform_y.png
platformer/img/restart_btn.png
platformer/img/save_btn.png
platformer/img/sky.png
platformer/img/start_btn.png
platformer/img/sun.png
platformer/levels/level0_data
platformer/levels/level1_data
platformer/levels/level2_data
platformer/levels/level3_data
platformer/levels/level4_data
platformer/levels/level5_data
platformer/levels/level6_data
platformer/levels/level7_data
TheOGPlatformer-1.0.dist-info/METADATA
TheOGPlatformer-1.0.dist-info/WHEEL
TheOGPlatformer-1.0.dist-info/entry_points.txt
TheOGPlatformer-1.0.dist-info/top_level.txt
TheOGPlatformer-1.0.dist-info/RECORD
