Metadata-Version: 2.1
Name: TheOGPlatformer
Version: 1.0
Summary: A simple yet fun platformer
Author: Yusuf
Author-email: yusufdeesawala72@gmail.com
Classifier: Programming Language :: Python :: 3
Classifier: License :: OSI Approved :: MIT License
Classifier: Operating System :: OS Independent
Requires-Python: >=3.6
Requires-Dist: pygame
